{"Path":"","Timestamp":1675206841000,"Items":[{"TypeId":3,"Type":"Codeunit","Id":50100,"Name":"ProcesosProyectos","TargetObject":"","TargetObjectType":"Codeunit","Publisher":"MaybeCloud","Application":"Proyectos_Avanzados","Version":"1.0.2.8","CanExecute":false,"CanDesign":false,"FsPath":"","EventName":"OnBeforeCreateDimSetFromJobTaskDimMyB","EventType":"EventSubscriber","EventPublisher":false,"TargetEventName":"OnBeforeCreateDimSetFromJobTaskDim","TargetElementName":"","EventParameters":[{"Name":"JobNo","TypeDefinition":{"Name":"Code[20]","Temporary":false}},{"Name":"JobTaskNo","TypeDefinition":{"Name":"Code[20]","Temporary":false}},{"IsVar":true,"Name":"GlobalDimVal1","TypeDefinition":{"Name":"Code[20]","Temporary":false}},{"IsVar":true,"Name":"GlobalDimVal2","TypeDefinition":{"Name":"Code[20]","Temporary":false}},{"IsVar":true,"Name":"NewDimSetID","TypeDefinition":{"Name":"Integer","Temporary":false}},{"IsVar":true,"Name":"IsHandled","TypeDefinition":{"Name":"Boolean","Temporary":false}}],"FieldName":"","SymbolData":null},{"TypeId":3,"Type":"Codeunit","Id":50100,"Name":"ProcesosProyectos","TargetObject":"","TargetObjectType":"","Publisher":"MaybeCloud","Application":"Proyectos_Avanzados","Version":"1.0.2.8","CanExecute":false,"CanDesign":false,"FsPath":"","EventName":"OnAfterCreatePurchaseInvoiceLines","EventType":"IntegrationEvent","EventPublisher":true,"TargetEventName":"","TargetElementName":"","EventParameters":[{"Name":"PurchaseHeader","TypeDefinition":{"Name":"Record","Subtype":{"Name":"Purchase Header","Id":38,"IsEmpty":false},"Temporary":false}},{"Name":"NewInvoice","TypeDefinition":{"Name":"Boolean","Temporary":false}}],"FieldName":"","SymbolData":null},{"TypeId":3,"Type":"Codeunit","Id":50100,"Name":"ProcesosProyectos","TargetObject":"","TargetObjectType":"","Publisher":"MaybeCloud","Application":"Proyectos_Avanzados","Version":"1.0.2.8","CanExecute":false,"CanDesign":false,"FsPath":"","EventName":"OnAfterCreatePurchaseLine","EventType":"IntegrationEvent","EventPublisher":true,"TargetEventName":"","TargetElementName":"","EventParameters":[{"IsVar":true,"Name":"PurchaseLine","TypeDefinition":{"Name":"Record","Subtype":{"Name":"Purchase Line","Id":39,"IsEmpty":false},"Temporary":false}},{"Name":"PurchaseHeader","TypeDefinition":{"Name":"Record","Subtype":{"Name":"Purchase Header","Id":38,"IsEmpty":false},"Temporary":false}},{"Name":"Job","TypeDefinition":{"Name":"Record","Subtype":{"Name":"Job","Id":167,"IsEmpty":false},"Temporary":false}},{"Name":"JobPlanningLine","TypeDefinition":{"Name":"Record","Subtype":{"Name":"Job Planning Line","Id":1003,"IsEmpty":false},"Temporary":false}}],"FieldName":"","SymbolData":null},{"TypeId":3,"Type":"Codeunit","Id":50100,"Name":"ProcesosProyectos","TargetObject":"","TargetObjectType":"","Publisher":"MaybeCloud","Application":"Proyectos_Avanzados","Version":"1.0.2.8","CanExecute":false,"CanDesign":false,"FsPath":"","EventName":"OnBeforeCreatePurchaseInvoiceLines","EventType":"IntegrationEvent","EventPublisher":true,"TargetEventName":"","TargetElementName":"","EventParameters":[{"IsVar":true,"Name":"JobPlanningLine","TypeDefinition":{"Name":"Record","Subtype":{"Name":"Job Planning Line","Id":1003,"IsEmpty":false},"Temporary":false}},{"Name":"InvoiceNo","TypeDefinition":{"Name":"Code[20]","Temporary":false}},{"Name":"NewInvoice","TypeDefinition":{"Name":"Boolean","Temporary":false}},{"Name":"PostingDate","TypeDefinition":{"Name":"Date","Temporary":false}},{"Name":"CreditMemo","TypeDefinition":{"Name":"Boolean","Temporary":false}}],"FieldName":"","SymbolData":null},{"TypeId":3,"Type":"Codeunit","Id":50100,"Name":"ProcesosProyectos","TargetObject":"","TargetObjectType":"","Publisher":"MaybeCloud","Application":"Proyectos_Avanzados","Version":"1.0.2.8","CanExecute":false,"CanDesign":false,"FsPath":"","EventName":"OnBeforeDeletePurchaseLine","EventType":"IntegrationEvent","EventPublisher":true,"TargetEventName":"","TargetElementName":"","EventParameters":[{"IsVar":true,"Name":"PurchaseLine","TypeDefinition":{"Name":"Record","Subtype":{"Name":"Purchase Line","Id":39,"IsEmpty":false},"Temporary":false}},{"IsVar":true,"Name":"IsHandled","TypeDefinition":{"Name":"Boolean","Temporary":false}}],"FieldName":"","SymbolData":null},{"TypeId":3,"Type":"Codeunit","Id":50100,"Name":"ProcesosProyectos","TargetObject":"","TargetObjectType":"","Publisher":"MaybeCloud","Application":"Proyectos_Avanzados","Version":"1.0.2.8","CanExecute":false,"CanDesign":false,"FsPath":"","EventName":"OnBeforeGetInvoiceNo","EventType":"IntegrationEvent","EventPublisher":true,"TargetEventName":"","TargetElementName":"","EventParameters":[{"Name":"JobPlanningLine","TypeDefinition":{"Name":"Record","Subtype":{"Name":"Job Planning Line","Id":1003,"IsEmpty":false},"Temporary":false}},{"Name":"Done","TypeDefinition":{"Name":"Boolean","Temporary":false}},{"Name":"NewInvoice","TypeDefinition":{"Name":"Boolean","Temporary":false}},{"Name":"PostingDate","TypeDefinition":{"Name":"Date","Temporary":false}},{"IsVar":true,"Name":"InvoiceNo","TypeDefinition":{"Name":"Code[20]","Temporary":false}},{"IsVar":true,"Name":"IsHandled","TypeDefinition":{"Name":"Boolean","Temporary":false}}],"FieldName":"","SymbolData":null},{"TypeId":3,"Type":"Codeunit","Id":50100,"Name":"ProcesosProyectos","TargetObject":"","TargetObjectType":"","Publisher":"MaybeCloud","Application":"Proyectos_Avanzados","Version":"1.0.2.8","CanExecute":false,"CanDesign":false,"FsPath":"","EventName":"OnBeforeGetCrMemoNo","EventType":"IntegrationEvent","EventPublisher":true,"TargetEventName":"","TargetElementName":"","EventParameters":[{"Name":"JobPlanningLine","TypeDefinition":{"Name":"Record","Subtype":{"Name":"Job Planning Line","Id":1003,"IsEmpty":false},"Temporary":false}},{"Name":"Done","TypeDefinition":{"Name":"Boolean","Temporary":false}},{"Name":"NewInvoice","TypeDefinition":{"Name":"Boolean","Temporary":false}},{"Name":"PostingDate","TypeDefinition":{"Name":"Date","Temporary":false}},{"IsVar":true,"Name":"InvoiceNo","TypeDefinition":{"Name":"Code[20]","Temporary":false}},{"IsVar":true,"Name":"IsHandled","TypeDefinition":{"Name":"Boolean","Temporary":false}}],"FieldName":"","SymbolData":null},{"TypeId":3,"Type":"Codeunit","Id":50100,"Name":"ProcesosProyectos","TargetObject":"","TargetObjectType":"","Publisher":"MaybeCloud","Application":"Proyectos_Avanzados","Version":"1.0.2.8","CanExecute":false,"CanDesign":false,"FsPath":"","EventName":"OnBeforeInsertPurchaseHeader","EventType":"IntegrationEvent","EventPublisher":true,"TargetEventName":"","TargetElementName":"","EventParameters":[{"IsVar":true,"Name":"PurchaseHeader","TypeDefinition":{"Name":"Record","Subtype":{"Name":"Purchase Header","Id":38,"IsEmpty":false},"Temporary":false}},{"Name":"Job","TypeDefinition":{"Name":"Record","Subtype":{"Name":"Job","Id":167,"IsEmpty":false},"Temporary":false}}],"FieldName":"","SymbolData":null},{"TypeId":3,"Type":"Codeunit","Id":50100,"Name":"ProcesosProyectos","TargetObject":"","TargetObjectType":"","Publisher":"MaybeCloud","Application":"Proyectos_Avanzados","Version":"1.0.2.8","CanExecute":false,"CanDesign":false,"FsPath":"","EventName":"OnBeforeModifyPurchaseHeader","EventType":"IntegrationEvent","EventPublisher":true,"TargetEventName":"","TargetElementName":"","EventParameters":[{"IsVar":true,"Name":"PurchaseHeader","TypeDefinition":{"Name":"Record","Subtype":{"Name":"Purchase Header","Id":38,"IsEmpty":false},"Temporary":false}},{"Name":"Job","TypeDefinition":{"Name":"Record","Subtype":{"Name":"Job","Id":167,"IsEmpty":false},"Temporary":false}}],"FieldName":"","SymbolData":null},{"TypeId":3,"Type":"Codeunit","Id":50100,"Name":"ProcesosProyectos","TargetObject":"","TargetObjectType":"","Publisher":"MaybeCloud","Application":"Proyectos_Avanzados","Version":"1.0.2.8","CanExecute":false,"CanDesign":false,"FsPath":"","EventName":"OnBeforeInsertPurchaseLine","EventType":"IntegrationEvent","EventPublisher":true,"TargetEventName":"","TargetElementName":"","EventParameters":[{"IsVar":true,"Name":"PurchaseLine","TypeDefinition":{"Name":"Record","Subtype":{"Name":"Purchase Line","Id":39,"IsEmpty":false},"Temporary":false}},{"Name":"PurchaseHeader","TypeDefinition":{"Name":"Record","Subtype":{"Name":"Purchase Header","Id":38,"IsEmpty":false},"Temporary":false}},{"Name":"Job","TypeDefinition":{"Name":"Record","Subtype":{"Name":"Job","Id":167,"IsEmpty":false},"Temporary":false}},{"Name":"JobPlanningLine","TypeDefinition":{"Name":"Record","Subtype":{"Name":"Job Planning Line","Id":1003,"IsEmpty":false},"Temporary":false}}],"FieldName":"","SymbolData":null},{"TypeId":3,"Type":"Codeunit","Id":50100,"Name":"ProcesosProyectos","TargetObject":"","TargetObjectType":"","Publisher":"MaybeCloud","Application":"Proyectos_Avanzados","Version":"1.0.2.8","CanExecute":false,"CanDesign":false,"FsPath":"","EventName":"OnBeforeModifyPurchaseLine","EventType":"IntegrationEvent","EventPublisher":true,"TargetEventName":"","TargetElementName":"","EventParameters":[{"IsVar":true,"Name":"PurchaseLine","TypeDefinition":{"Name":"Record","Subtype":{"Name":"Purchase Line","Id":39,"IsEmpty":false},"Temporary":false}},{"Name":"PurchaseHeader","TypeDefinition":{"Name":"Record","Subtype":{"Name":"Purchase Header","Id":38,"IsEmpty":false},"Temporary":false}},{"Name":"Job","TypeDefinition":{"Name":"Record","Subtype":{"Name":"Job","Id":167,"IsEmpty":false},"Temporary":false}},{"Name":"JobPlanningLine","TypeDefinition":{"Name":"Record","Subtype":{"Name":"Job Planning Line","Id":1003,"IsEmpty":false},"Temporary":false}}],"FieldName":"","SymbolData":null},{"TypeId":3,"Type":"Codeunit","Id":50100,"Name":"ProcesosProyectos","TargetObject":"","TargetObjectType":"","Publisher":"MaybeCloud","Application":"Proyectos_Avanzados","Version":"1.0.2.8","CanExecute":false,"CanDesign":false,"FsPath":"","EventName":"OnBeforeOpenPurchaseInvoice","EventType":"IntegrationEvent","EventPublisher":true,"TargetEventName":"","TargetElementName":"","EventParameters":[{"IsVar":true,"Name":"JobPlanningLineInvoice","TypeDefinition":{"Name":"Record","Subtype":{"Name":"Job Planning Line Invoice","Id":1022,"IsEmpty":false},"Temporary":false}},{"IsVar":true,"Name":"IsHandled","TypeDefinition":{"Name":"Boolean","Temporary":false}}],"FieldName":"","SymbolData":null},{"TypeId":3,"Type":"Codeunit","Id":50100,"Name":"ProcesosProyectos","TargetObject":"","TargetObjectType":"","Publisher":"MaybeCloud","Application":"Proyectos_Avanzados","Version":"1.0.2.8","CanExecute":false,"CanDesign":false,"FsPath":"","EventName":"OnBeforeTestPurchaseHeader","EventType":"IntegrationEvent","EventPublisher":true,"TargetEventName":"","TargetElementName":"","EventParameters":[{"IsVar":true,"Name":"PurchaseHeader","TypeDefinition":{"Name":"Record","Subtype":{"Name":"Purchase Header","Id":38,"IsEmpty":false},"Temporary":false}},{"Name":"Job","TypeDefinition":{"Name":"Record","Subtype":{"Name":"Job","Id":167,"IsEmpty":false},"Temporary":false}},{"IsVar":true,"Name":"IsHandled","TypeDefinition":{"Name":"Boolean","Temporary":false}}],"FieldName":"","SymbolData":null},{"TypeId":3,"Type":"Codeunit","Id":50100,"Name":"ProcesosProyectos","TargetObject":"","TargetObjectType":"","Publisher":"MaybeCloud","Application":"Proyectos_Avanzados","Version":"1.0.2.8","CanExecute":false,"CanDesign":false,"FsPath":"","EventName":"OnBeforeUpdatePurchaseHeader","EventType":"IntegrationEvent","EventPublisher":true,"TargetEventName":"","TargetElementName":"","EventParameters":[{"IsVar":true,"Name":"PurchaseHeader","TypeDefinition":{"Name":"Record","Subtype":{"Name":"Purchase Header","Id":38,"IsEmpty":false},"Temporary":false}},{"Name":"Job","TypeDefinition":{"Name":"Record","Subtype":{"Name":"Job","Id":167,"IsEmpty":false},"Temporary":false}},{"IsVar":true,"Name":"IsHandled","TypeDefinition":{"Name":"Boolean","Temporary":false}}],"FieldName":"","SymbolData":null},{"TypeId":3,"Type":"Codeunit","Id":50100,"Name":"ProcesosProyectos","TargetObject":"","TargetObjectType":"","Publisher":"MaybeCloud","Application":"Proyectos_Avanzados","Version":"1.0.2.8","CanExecute":false,"CanDesign":false,"FsPath":"","EventName":"OnAfterTestPurchaseHeader","EventType":"IntegrationEvent","EventPublisher":true,"TargetEventName":"","TargetElementName":"","EventParameters":[{"IsVar":true,"Name":"PurchaseHeader","TypeDefinition":{"Name":"Record","Subtype":{"Name":"Purchase Header","Id":38,"IsEmpty":false},"Temporary":false}},{"Name":"Job","TypeDefinition":{"Name":"Record","Subtype":{"Name":"Job","Id":167,"IsEmpty":false},"Temporary":false}}],"FieldName":"","SymbolData":null},{"TypeId":3,"Type":"Codeunit","Id":50100,"Name":"ProcesosProyectos","TargetObject":"","TargetObjectType":"","Publisher":"MaybeCloud","Application":"Proyectos_Avanzados","Version":"1.0.2.8","CanExecute":false,"CanDesign":false,"FsPath":"","EventName":"OnCreatePurchaseHeaderOnBeforeUpdatePurchaseHeader","EventType":"IntegrationEvent","EventPublisher":true,"TargetEventName":"","TargetElementName":"","EventParameters":[{"IsVar":true,"Name":"PurchaseHeader","TypeDefinition":{"Name":"Record","Subtype":{"Name":"Purchase Header","Id":38,"IsEmpty":false},"Temporary":false}},{"IsVar":true,"Name":"Job","TypeDefinition":{"Name":"Record","Subtype":{"Name":"Job","Id":167,"IsEmpty":false},"Temporary":false}},{"IsVar":true,"Name":"IsHandled","TypeDefinition":{"Name":"Boolean","Temporary":false}}],"FieldName":"","SymbolData":null},{"TypeId":3,"Type":"Codeunit","Id":50100,"Name":"ProcesosProyectos","TargetObject":"","TargetObjectType":"","Publisher":"MaybeCloud","Application":"Proyectos_Avanzados","Version":"1.0.2.8","CanExecute":false,"CanDesign":false,"FsPath":"","EventName":"OnCreatePurchaseInvoiceLinesOnBeforeCreatePurchaseLine","EventType":"IntegrationEvent","EventPublisher":true,"TargetEventName":"","TargetElementName":"","EventParameters":[{"IsVar":true,"Name":"JobPlanningLine","TypeDefinition":{"Name":"Record","Subtype":{"Name":"Job Planning Line","Id":1003,"IsEmpty":false},"Temporary":false}},{"Name":"PurchaseHeader","TypeDefinition":{"Name":"Record","Subtype":{"Name":"Purchase Header","Id":38,"IsEmpty":false},"Temporary":false}},{"IsVar":true,"Name":"PurchaseHeader2","TypeDefinition":{"Name":"Record","Subtype":{"Name":"Purchase Header","Id":38,"IsEmpty":false},"Temporary":false}},{"Name":"NewInvoice","TypeDefinition":{"Name":"Boolean","Temporary":false}}],"FieldName":"","SymbolData":null},{"TypeId":3,"Type":"Codeunit","Id":50100,"Name":"ProcesosProyectos","TargetObject":"","TargetObjectType":"","Publisher":"MaybeCloud","Application":"Proyectos_Avanzados","Version":"1.0.2.8","CanExecute":false,"CanDesign":false,"FsPath":"","EventName":"OnCreatePurchaseInvoiceLinesOnBeforeGetCustomer","EventType":"IntegrationEvent","EventPublisher":true,"TargetEventName":"","TargetElementName":"","EventParameters":[{"Name":"JobPlanningLine","TypeDefinition":{"Name":"Record","Subtype":{"Name":"Job Planning Line","Id":1003,"IsEmpty":false},"Temporary":false}},{"IsVar":true,"Name":"Customer","TypeDefinition":{"Name":"Record","Subtype":{"Name":"Customer","Id":18,"IsEmpty":false},"Temporary":false}},{"IsVar":true,"Name":"IsHandled","TypeDefinition":{"Name":"Boolean","Temporary":false}}],"FieldName":"","SymbolData":null},{"TypeId":3,"Type":"Codeunit","Id":50100,"Name":"ProcesosProyectos","TargetObject":"","TargetObjectType":"","Publisher":"MaybeCloud","Application":"Proyectos_Avanzados","Version":"1.0.2.8","CanExecute":false,"CanDesign":false,"FsPath":"","EventName":"OnCreatePurchaseInvoiceJobTaskOnBeforeCreatePurchaseLine","EventType":"IntegrationEvent","EventPublisher":true,"TargetEventName":"","TargetElementName":"","EventParameters":[{"IsVar":true,"Name":"JobPlanningLine","TypeDefinition":{"Name":"Record","Subtype":{"Name":"Job Planning Line","Id":1003,"IsEmpty":false},"Temporary":false}},{"Name":"PurchaseHeader","TypeDefinition":{"Name":"Record","Subtype":{"Name":"Purchase Header","Id":38,"IsEmpty":false},"Temporary":false}},{"IsVar":true,"Name":"PurchaseHeader2","TypeDefinition":{"Name":"Record","Subtype":{"Name":"Purchase Header","Id":38,"IsEmpty":false},"Temporary":false}}],"FieldName":"","SymbolData":null},{"TypeId":3,"Type":"Codeunit","Id":50100,"Name":"ProcesosProyectos","TargetObject":"","TargetObjectType":"","Publisher":"MaybeCloud","Application":"Proyectos_Avanzados","Version":"1.0.2.8","CanExecute":false,"CanDesign":false,"FsPath":"","EventName":"OnBeforeCreatePurchaseLine","EventType":"IntegrationEvent","EventPublisher":true,"TargetEventName":"","TargetElementName":"","EventParameters":[{"IsVar":true,"Name":"JobPlanningLine","TypeDefinition":{"Name":"Record","Subtype":{"Name":"Job Planning Line","Id":1003,"IsEmpty":false},"Temporary":false}},{"IsVar":true,"Name":"PurchaseHeader","TypeDefinition":{"Name":"Record","Subtype":{"Name":"Purchase Header","Id":38,"IsEmpty":false},"Temporary":false}},{"IsVar":true,"Name":"PurchaseHeader2","TypeDefinition":{"Name":"Record","Subtype":{"Name":"Purchase Header","Id":38,"IsEmpty":false},"Temporary":false}},{"IsVar":true,"Name":"JobInvCurrency","TypeDefinition":{"Name":"Boolean","Temporary":false}}],"FieldName":"","SymbolData":null},{"TypeId":3,"Type":"Codeunit","Id":50101,"Name":"Eventos-proyectos","TargetObject":"","TargetObjectType":"Codeunit","Publisher":"MaybeCloud","Application":"Proyectos_Avanzados","Version":"1.0.2.8","CanExecute":false,"CanDesign":false,"FsPath":"","EventName":"OnRunOnBeforePostPurchLineMyb","EventType":"EventSubscriber","EventPublisher":false,"TargetEventName":"OnRunOnBeforePostPurchLine","TargetElementName":"","EventParameters":[{"IsVar":true,"Name":"PurchLine","TypeDefinition":{"Name":"Record","Subtype":{"Name":"Purchase Line","Id":39,"IsEmpty":false},"Temporary":false}},{"IsVar":true,"Name":"PurchHeader","TypeDefinition":{"Name":"Record","Subtype":{"Name":"Purchase Header","Id":38,"IsEmpty":false},"Temporary":false}}],"FieldName":"","SymbolData":null},{"TypeId":3,"Type":"Codeunit","Id":50101,"Name":"Eventos-proyectos","TargetObject":"","TargetObjectType":"Table","Publisher":"MaybeCloud","Application":"Proyectos_Avanzados","Version":"1.0.2.8","CanExecute":false,"CanDesign":false,"FsPath":"","EventName":"OnBeforeOnInsertMyB","EventType":"EventSubscriber","EventPublisher":false,"TargetEventName":"OnBeforeOnInsert","TargetElementName":"","EventParameters":[{"IsVar":true,"Name":"JobPlanningLine","TypeDefinition":{"Name":"Record","Subtype":{"Name":"Job Planning Line","Id":1003,"IsEmpty":false},"Temporary":false}},{"IsVar":true,"Name":"IsHandled","TypeDefinition":{"Name":"Boolean","Temporary":false}}],"FieldName":"","SymbolData":null},{"TypeId":9,"Type":"TableExtension","Id":50102,"Name":"PurcharseLine_Job","TargetObject":"","TargetObjectType":"","Publisher":"MaybeCloud","Application":"Proyectos_Avanzados","Version":"1.0.2.8","CanExecute":false,"CanDesign":false,"FsPath":"","EventName":"OnBeforeValidateJobContractEntryNo","EventType":"InternalEvent","EventPublisher":true,"TargetEventName":"","TargetElementName":"","EventParameters":[{"IsVar":true,"Name":"xRec","TypeDefinition":{"Name":"Record","Subtype":{"Name":"Purchase Line","Id":39,"IsEmpty":false},"Temporary":false}},{"IsVar":true,"Name":"IsHandled","TypeDefinition":{"Name":"Boolean","Temporary":false}}],"FieldName":"","SymbolData":null}],"CreatedwithVersion":"0.2.4"}
